pystdapi/__init__.py
pystdapi/app.py
pystdapi/cli.py
pystdapi/exceptions.py
pystdapi/middleware.py
pystdapi/plugins.py
pystdapi/requests.py
pystdapi/responses.py
pystdapi/routing.py
pystdapi/server.py
pystdapi/templates.py
pystdapi/utils.py
pystdapi-0.1.2.dist-info/LICENSE
pystdapi-0.1.2.dist-info/METADATA
pystdapi-0.1.2.dist-info/WHEEL
pystdapi-0.1.2.dist-info/top_level.txt
pystdapi-0.1.2.dist-info/RECORD
