Metadata-Version: 2.1
Name: pystdapi
Version: 0.1.2
Summary: 纯异步 Python Web 框架，仅依赖 Python 标准库
Home-page: https://gitee.com/wangweiyong/pystdapi
Author: 王伟勇
Author-email: 王伟勇 <909094426@qq.com>
License: MIT
Project-URL: Homepage, https://gitee.com/wangweiyong/pystdapi
Project-URL: Documentation, https://gitee.com/wangweiyong/pystdapi#readme
Keywords: asgi,web,framework,async,python,standard-library
Classifier: Development Status :: 4 - Beta
Classifier: Intended Audience :: Developers
Classifier: License :: OSI Approved :: MIT License
Classifier: Programming Language :: Python :: 3
Classifier: Programming Language :: Python :: 3.7
Classifier: Programming Language :: Python :: 3.8
Classifier: Programming Language :: Python :: 3.9
Classifier: Programming Language :: Python :: 3.10
Classifier: Programming Language :: Python :: 3.11
Classifier: Programming Language :: Python :: 3.12
Classifier: Topic :: Internet :: WWW/HTTP
Classifier: Topic :: Internet :: WWW/HTTP :: Dynamic Content
Classifier: Topic :: Internet :: WWW/HTTP :: HTTP Servers
Classifier: Topic :: Software Development :: Libraries :: Application Frameworks
Requires-Python: >=3.7
License-File: LICENSE
